kor/__init__.py
kor/_pydantic.py
kor/adapters.py
kor/documents/__init__.py
kor/documents/html.py
kor/documents/typedefs.py
kor/encoders/__init__.py
kor/encoders/csv_data.py
kor/encoders/encode.py
kor/encoders/json_data.py
kor/encoders/typedefs.py
kor/encoders/utils.py
kor/encoders/xml.py
kor/examples.py
kor/exceptions.py
kor/extraction/__init__.py
kor/extraction/api.py
kor/extraction/parser.py
kor/extraction/typedefs.py
kor/nodes.py
kor/prompts.py
kor/py.typed
kor/type_descriptors.py
kor/validators.py
kor/version.py
kor-3.0.0.dist-info/LICENSE
kor-3.0.0.dist-info/METADATA
kor-3.0.0.dist-info/WHEEL
kor-3.0.0.dist-info/RECORD
