Metadata-Version: 2.1
Name: kor
Version: 3.0.0
Summary: Extract information with LLMs from text
Home-page: https://www.github.com/eyurtsev/kor
License: MIT
Author: Eugene Yurtsev
Author-email: eyurtsev@gmail.com
Requires-Python: >=3.9,<4.0
Classifier: License :: OSI Approved :: MIT License
Classifier: Programming Language :: Python :: 3
Classifier: Programming Language :: Python :: 3.9
Classifier: Programming Language :: Python :: 3.10
Classifier: Programming Language :: Python :: 3.11
Provides-Extra: html
Requires-Dist: langchain-core (>=0.3,<0.4)
Requires-Dist: markdownify (>=0.11.6,<0.12.0) ; extra == "html"
Requires-Dist: pandas (>=1.5.3,<3)
Requires-Dist: pydantic (>=2,<3)
Project-URL: Repository, https://www.github.com/eyurtsev/kor
